{
  "version": 1,
  "dashboard": {
    "bind": "tailscale",
    "port": 8088,
    "url": "https://oreochiserver.tail0a3a58.ts.net:8448"
  },
  "api": {
    "bind": "127.0.0.1",
    "port": 8099,
    "public": false
  },
  "observed": {
    "tailscaleIp": "100.75.210.83",
    "funnel": {
      "enabled": false,
      "url": "",
      "target": "",
      "allowedInP0": false
    }
  },
  "workloadRoutes": {
    "intake-os": {
      "tailnet": {
        "enabled": true,
        "mode": "tailscale-serve",
        "url": "https://oreochiserver.tail0a3a58.ts.net:8444"
      },
      "cloudflare": {
        "enabled": false,
        "hostname": "",
        "mode": "disabled",
        "requiresAuth": true
      }
    },
    "hastur": {
      "tailnet": {
        "enabled": true,
        "mode": "tailscale-serve",
        "url": "https://oreochiserver.tail0a3a58.ts.net:8445"
      },
      "cloudflare": {
        "enabled": false,
        "hostname": "",
        "mode": "disabled",
        "requiresAuth": true
      }
    },
    "uptime-kuma": {
      "tailnet": {
        "enabled": true,
        "mode": "tailscale-serve",
        "url": "https://oreochiserver.tail0a3a58.ts.net:8446"
      },
      "cloudflare": {
        "enabled": false,
        "hostname": "",
        "mode": "disabled",
        "requiresAuth": true
      }
    },
    "review-ui": {
      "tailnet": {
        "enabled": true,
        "mode": "tailscale-serve",
        "url": "https://oreochiserver.tail0a3a58.ts.net:8447"
      },
      "cloudflare": {
        "enabled": false,
        "hostname": "",
        "mode": "disabled",
        "requiresAuth": true
      }
    },
    "dozzle": {
      "tailnet": {
        "enabled": false,
        "mode": "local-only",
        "url": ""
      },
      "cloudflare": {
        "enabled": false,
        "hostname": "",
        "mode": "blocked",
        "requiresAuth": true
      }
    },
    "hello-nginx": {
      "tailnet": {
        "enabled": false,
        "mode": "blocked",
        "url": ""
      },
      "cloudflare": {
        "enabled": false,
        "hostname": "hello-nginx.argus.invalid",
        "mode": "planned",
        "requiresAuth": true
      }
    },
    "locigraph": {
      "tailnet": {
        "enabled": false,
        "mode": "local-only",
        "url": ""
      },
      "cloudflare": {
        "enabled": false,
        "hostname": "",
        "mode": "disabled",
        "requiresAuth": true
      }
    },
    "kadath": {
      "tailnet": {
        "enabled": true,
        "mode": "tailscale-serve",
        "url": "https://oreochiserver.tail0a3a58.ts.net:8443"
      },
      "cloudflare": {
        "enabled": false,
        "hostname": "",
        "mode": "disabled",
        "requiresAuth": true
      }
    }
  }
}
